screengrid/__init__.py
screengrid/grid.py
screengrid/main.py
screengrid/rectangle.py
screengrid/screencanvas.py
screengrid/win32_contants.py
screengrid-0.0.16.dist-info/LICENSE
screengrid-0.0.16.dist-info/METADATA
screengrid-0.0.16.dist-info/WHEEL
screengrid-0.0.16.dist-info/top_level.txt
screengrid-0.0.16.dist-info/RECORD
